foothold_sitac/__init__.py
foothold_sitac/config.py
foothold_sitac/dependencies.py
foothold_sitac/foothold.py
foothold_sitac/foothold_api_router.py
foothold_sitac/foothold_router.py
foothold_sitac/main.py
foothold_sitac/schemas.py
foothold_sitac/static/css/base.css
foothold_sitac/static/css/cards.css
foothold_sitac/static/css/map.css
foothold_sitac/static/css/modals.css
foothold_sitac/static/css/navbar.css
foothold_sitac/static/css/sitac.css
foothold_sitac/static/favicon.ico
foothold_sitac/static/js/coords.js
foothold_sitac/static/js/map.js
foothold_sitac/static/js/modals.js
foothold_sitac/templater.py
foothold_sitac/templates/base.html
foothold_sitac/templates/foothold/map.html
foothold_sitac/templates/foothold/partials/ejected.html
foothold_sitac/templates/foothold/partials/missions.html
foothold_sitac/templates/foothold/partials/players.html
foothold_sitac/templates/foothold/partials/zones.html
foothold_sitac/templates/foothold/servers.html
foothold_sitac/templates/foothold/sitac.html
foothold_sitac/templates/home.html
foothold_sitac-0.1.0.dist-info/METADATA
foothold_sitac-0.1.0.dist-info/WHEEL
foothold_sitac-0.1.0.dist-info/RECORD
