Metadata-Version: 2.1
Name: foothold-sitac
Version: 0.1.0
Summary: Web application displaying tactical maps for DCS World Foothold missions
License: MIT
Author: Michel NAUD
Author-email: michel.naud26400@gmail.com
Requires-Python: >=3.12,<4.0
Classifier: Development Status :: 4 - Beta
Classifier: Framework :: FastAPI
Classifier: License :: OSI Approved :: MIT License
Classifier: Programming Language :: Python :: 3
Classifier: Programming Language :: Python :: 3.12
Classifier: Topic :: Games/Entertainment :: Simulation
Requires-Dist: fastapi (>=0.121.1,<0.122.0)
Requires-Dist: jinja2 (>=3.1.6,<4.0.0)
Requires-Dist: lupa (>=2.6,<3.0)
Requires-Dist: pydantic (>=2.12.4,<3.0.0)
Requires-Dist: pyyaml (>=6.0.3,<7.0.0)
Requires-Dist: uvicorn (>=0.38.0,<0.39.0)
